geometry_packer/__init__.py
geometry_packer/geometry_packer.py
geometry_packer/utils.py
geometry_packer-0.1.0.dist-info/METADATA
geometry_packer-0.1.0.dist-info/WHEEL
geometry_packer-0.1.0.dist-info/top_level.txt
geometry_packer-0.1.0.dist-info/RECORD
