Metadata-Version: 2.1
Name: geometry_packer
Version: 0.1.0
Summary: A Python package for efficient packing and manipulation of geometric shapes in 2D and 3D domains, tailored for RVE and related applications.
Author-email: Rajesh Nakka <338rajesh@gmail.com>
Maintainer-email: Rajesh Nakka <338rajesh@gmail.com>
Project-URL: documentation, https://geometry_packer.readthedocs.io
Project-URL: repository, https://github.com/338rajesh/geometry_packer
Keywords: RVE,RUC,Unit Cell
Classifier: Programming Language :: Python :: 3
Classifier: License :: OSI Approved :: MIT License
Classifier: Operating System :: OS Independent
Requires-Dist: numpy==2.2.0
Requires-Dist: matplotlib==3.10.0
Requires-Dist: gbox==0.2.0
